facpy/__init__.py
facpy/geo.py
facpy/grid.py
facpy/ihfac.py
facpy/io.py
facpy/plot.py
facpy/quiet.py
facpy-0.1.3.dist-info/METADATA
facpy-0.1.3.dist-info/WHEEL
facpy-0.1.3.dist-info/top_level.txt
facpy-0.1.3.dist-info/RECORD
