Metadata-Version: 2.4
Name: facpy
Version: 0.1.3
Summary: Field-Aligned Current Python toolkit for SWARM satellite analysis
Author-email: Edwin Ayabie <edwin.beshel@ejust.edu.eg>
Project-URL: Homepage, https://github.com/madvirus-ops/facpy
Project-URL: Bug Tracker, https://github.com/madvirus-ops/facpy/issues
Project-URL: Documentation, https://github.com/madvirus-ops/facpy#readme
Project-URL: Source Code, https://github.com/madvirus-ops/facpy
Classifier: Programming Language :: Python :: 3
Classifier: License :: OSI Approved :: MIT License
Classifier: Operating System :: OS Independent
Classifier: Topic :: Scientific/Engineering :: Physics
Requires-Python: >=3.9
Requires-Dist: numpy
Requires-Dist: pandas
Requires-Dist: polars
Requires-Dist: xarray
Requires-Dist: netCDF4
Requires-Dist: cdflib
Requires-Dist: cartopy
Requires-Dist: matplotlib
Requires-Dist: scipy
Requires-Dist: aacgmv2
Provides-Extra: dev
Requires-Dist: pytest; extra == "dev"
Requires-Dist: black; extra == "dev"
Requires-Dist: isort; extra == "dev"
Requires-Dist: flake8; extra == "dev"
Requires-Dist: mypy; extra == "dev"
